metric_learner/__init__.py
metric_learner/data_manager.py
metric_learner/metric_module.py
metric_learner/optimization.py
metric_learner/repl_interface.py
dspy_metric_learning-0.1.0rc1.dist-info/LICENSE
dspy_metric_learning-0.1.0rc1.dist-info/METADATA
dspy_metric_learning-0.1.0rc1.dist-info/WHEEL
dspy_metric_learning-0.1.0rc1.dist-info/RECORD
