Metadata-Version: 2.3
Name: dspy-metric-learning
Version: 0.1.0rc1
Summary: A DSPy metric function learning package
License: MIT
Keywords: dspy,metrics,machine learning,nlp,language models
Author: Tom Doerr
Author-email: tomdoerr96@gmail.com
Requires-Python: >=3.8,<4.0
Classifier: Development Status :: 2 - Pre-Alpha
Classifier: Intended Audience :: Developers
Classifier: Intended Audience :: Science/Research
Classifier: License :: OSI Approved :: MIT License
Classifier: Programming Language :: Python :: 3
Classifier: Programming Language :: Python :: 3.8
Classifier: Programming Language :: Python :: 3.9
Classifier: Programming Language :: Python :: 3.10
Classifier: Programming Language :: Python :: 3.11
Classifier: Programming Language :: Python :: 3.12
Classifier: Programming Language :: Python :: 3.13
Classifier: Topic :: Scientific/Engineering :: Artificial Intelligence
Requires-Dist: dspy-ai (>=2.0.0,<3.0.0)
Requires-Dist: numpy (>=1.24.0,<2.0.0)
Project-URL: Homepage, https://github.com/tom-doerr/dspy_metric_learning
Project-URL: Repository, https://github.com/tom-doerr/dspy_metric_learning
